topsis/__init__.py
topsis/__main__.py
Topsis_Himanshu_102017110-1.0.1.dist-info/LICENSE
Topsis_Himanshu_102017110-1.0.1.dist-info/METADATA
Topsis_Himanshu_102017110-1.0.1.dist-info/WHEEL
Topsis_Himanshu_102017110-1.0.1.dist-info/entry_points.txt
Topsis_Himanshu_102017110-1.0.1.dist-info/top_level.txt
Topsis_Himanshu_102017110-1.0.1.dist-info/RECORD
