Metadata-Version: 2.1
Name: Topsis-Himanshu-102017110
Version: 1.0.1
Summary: A Python package implementing TOPSIS technique.
Home-page: https://github.com/himanshu-1403/topsisImplementation
Author: Himanshu Nagpal
Author-email: himanshunagpal150@gmail.com
License: MIT
Platform: UNKNOWN
Classifier: License :: OSI Approved :: MIT License
Classifier: Programming Language :: Python :: 3
Classifier: Programming Language :: Python :: 3.7
Requires-Dist: numpy
Requires-Dist: pandas
